[
  {"dir":"src/cli/nodes-cli/register.ts","origin":"Manage gateway-owned node pairing","translate":"管理网关拥有的节点配对"},
  {"dir":"src/cli/nodes-cli/register.ts","origin":"Docs:","translate":"文档:"},
  {"dir":"src/cli/nodes-cli/register.camera.ts","origin":"Capture camera media from a paired node","translate":"从已配对节点获取摄像头媒体"},
  {"dir":"src/cli/nodes-cli/register.camera.ts","origin":"List available cameras on a node","translate":"列出节点上的可用摄像头"},
  {"dir":"src/cli/nodes-cli/register.camera.ts","origin":"Node id, name, or IP","translate":"节点 ID、名称或 IP"},
  {"dir":"src/cli/nodes-cli/register.camera.ts","origin":"No cameras reported.","translate":"未报告摄像头。"},
  {"dir":"src/cli/nodes-cli/register.camera.ts","origin":"Unknown Camera","translate":"未知摄像头"},
  {"dir":"src/cli/nodes-cli/register.camera.ts","origin":"unspecified","translate":"未指定"},
  {"dir":"src/cli/nodes-cli/register.camera.ts","origin":"Name","translate":"名称"},
  {"dir":"src/cli/nodes-cli/register.camera.ts","origin":"Position","translate":"位置"},
  {"dir":"src/cli/nodes-cli/register.camera.ts","origin":"ID","translate":"ID"},
  {"dir":"src/cli/nodes-cli/register.camera.ts","origin":"Capture a photo from a node camera (prints MEDIA:<path>)","translate":"从节点摄像头拍摄照片 (输出 MEDIA:<路径>)"},
  {"dir":"src/cli/nodes-cli/register.camera.ts","origin":"Camera facing","translate":"摄像头朝向"},
  {"dir":"src/cli/nodes-cli/register.camera.ts","origin":"Camera device id (from nodes camera list)","translate":"摄像头设备 ID (来自节点摄像头列表)"},
  {"dir":"src/cli/nodes-cli/register.camera.ts","origin":"Max width in px (optional)","translate":"最大宽度像素 (可选)"},
  {"dir":"src/cli/nodes-cli/register.camera.ts","origin":"JPEG quality (default 0.9)","translate":"JPEG 质量 (默认 0.9)"},
  {"dir":"src/cli/nodes-cli/register.camera.ts","origin":"Delay before capture in ms (macOS default 2000)","translate":"拍摄前延迟毫秒数 (macOS 默认 2000)"},
  {"dir":"src/cli/nodes-cli/register.camera.ts","origin":"Node invoke timeout in ms (default 20000)","translate":"节点调用超时毫秒数 (默认 20000)"},
  {"dir":"src/cli/nodes-cli/register.canvas.ts","origin":"Capture or render canvas content from a paired node","translate":"从已配对节点捕获或渲染画布内容"},
  {"dir":"src/cli/nodes-cli/register.canvas.ts","origin":"Capture a canvas snapshot (prints MEDIA:<path>)","translate":"捕获画布快照 (输出 MEDIA:<路径>)"},
  {"dir":"src/cli/nodes-cli/register.canvas.ts","origin":"Image format","translate":"图片格式"},
  {"dir":"src/cli/nodes-cli/register.canvas.ts","origin":"Max width in px (optional)","translate":"最大宽度像素 (可选)"},
  {"dir":"src/cli/nodes-cli/register.canvas.ts","origin":"JPEG quality (optional)","translate":"JPEG 质量 (可选)"},
  {"dir":"src/cli/nodes-cli/register.canvas.ts","origin":"Show the canvas (optionally with a target URL/path)","translate":"显示画布 (可选目标 URL/路径)"},
  {"dir":"src/cli/nodes-cli/register.canvas.ts","origin":"Target URL/path (optional)","translate":"目标 URL/路径 (可选)"},
  {"dir":"src/cli/nodes-cli/register.location.ts","origin":"Fetch location from a paired node","translate":"从已配对节点获取位置"},
  {"dir":"src/cli/nodes-cli/register.location.ts","origin":"Fetch the current location from a node","translate":"从节点获取当前位置"},
  {"dir":"src/cli/nodes-cli/register.location.ts","origin":"Use cached location newer than this (ms)","translate":"使用此时间内的缓存位置 (毫秒)"},
  {"dir":"src/cli/nodes-cli/register.location.ts","origin":"Desired accuracy (default: balanced/precise depending on node setting)","translate":"期望精度 (默认: 取决于节点设置的 balanced/precise)"},
  {"dir":"src/cli/nodes-cli/register.location.ts","origin":"Location fix timeout (ms)","translate":"定位超时 (毫秒)"},
  {"dir":"src/cli/nodes-cli/register.notify.ts","origin":"Send a local notification on a node (mac only)","translate":"在节点上发送本地通知 (仅限 mac)"},
  {"dir":"src/cli/nodes-cli/register.notify.ts","origin":"Notification title","translate":"通知标题"},
  {"dir":"src/cli/nodes-cli/register.notify.ts","origin":"Notification body","translate":"通知内容"},
  {"dir":"src/cli/nodes-cli/register.notify.ts","origin":"Notification sound","translate":"通知声音"},
  {"dir":"src/cli/nodes-cli/register.notify.ts","origin":"Notification priority","translate":"通知优先级"},
  {"dir":"src/cli/nodes-cli/register.notify.ts","origin":"Delivery mode","translate":"投递模式"},
  {"dir":"src/cli/nodes-cli/register.notify.ts","origin":"notify ok","translate":"通知已发送"},
  {"dir":"src/cli/nodes-cli/register.pairing.ts","origin":"List pending pairing requests","translate":"列出待处理的配对请求"},
  {"dir":"src/cli/nodes-cli/register.pairing.ts","origin":"No pending pairing requests.","translate":"无待处理的配对请求。"},
  {"dir":"src/cli/nodes-cli/register.pairing.ts","origin":"unknown","translate":"未知"},
  {"dir":"src/cli/nodes-cli/register.pairing.ts","origin":"yes","translate":"是"},
  {"dir":"src/cli/nodes-cli/register.pairing.ts","origin":"Request","translate":"请求"},
  {"dir":"src/cli/nodes-cli/register.pairing.ts","origin":"Node","translate":"节点"},
  {"dir":"src/cli/nodes-cli/register.pairing.ts","origin":"IP","translate":"IP"},
  {"dir":"src/cli/nodes-cli/register.pairing.ts","origin":"Requested","translate":"请求时间"},
  {"dir":"src/cli/nodes-cli/register.pairing.ts","origin":"Repair","translate":"修复"},
  {"dir":"src/cli/nodes-cli/register.pairing.ts","origin":"Approve a pending pairing request","translate":"批准待处理的配对请求"},
  {"dir":"src/cli/nodes-cli/register.pairing.ts","origin":"Pending request id","translate":"待处理请求 ID"},
  {"dir":"src/cli/nodes-cli/register.pairing.ts","origin":"Reject a pending pairing request","translate":"拒绝待处理的配对请求"},
  {"dir":"src/cli/nodes-cli/register.pairing.ts","origin":"Rename a paired node (display name override)","translate":"重命名已配对节点 (覆盖显示名称)"},
  {"dir":"src/cli/nodes-cli/register.pairing.ts","origin":"New display name","translate":"新显示名称"},
  {"dir":"src/cli/nodes-cli/register.pairing.ts","origin":"--node and --name required","translate":"需要 --node 和 --name"},
  {"dir":"src/cli/nodes-cli/register.screen.ts","origin":"Capture screen recordings from a paired node","translate":"从已配对节点捕获屏幕录制"},
  {"dir":"src/cli/nodes-cli/register.screen.ts","origin":"Capture a short screen recording from a node (prints MEDIA:<path>)","translate":"从节点捕获短屏幕录制 (输出 MEDIA:<路径>)"},
  {"dir":"src/cli/nodes-cli/register.screen.ts","origin":"Screen index (0 = primary)","translate":"屏幕索引 (0 = 主屏幕)"},
  {"dir":"src/cli/nodes-cli/register.screen.ts","origin":"Clip duration (ms or 10s)","translate":"片段时长 (毫秒或 10s)"},
  {"dir":"src/cli/nodes-cli/register.screen.ts","origin":"Frames per second","translate":"帧率"},
  {"dir":"src/cli/nodes-cli/register.screen.ts","origin":"Disable microphone audio capture","translate":"禁用麦克风音频捕获"},
  {"dir":"src/cli/nodes-cli/register.screen.ts","origin":"Output path","translate":"输出路径"},
  {"dir":"src/cli/nodes-cli/register.screen.ts","origin":"Node invoke timeout in ms (default 120000)","translate":"节点调用超时毫秒数 (默认 120000)"},
  {"dir":"src/cli/nodes-cli/register.status.ts","origin":"List known nodes with connection status and capabilities","translate":"列出已知节点及其连接状态和能力"},
  {"dir":"src/cli/nodes-cli/register.status.ts","origin":"Only show connected nodes","translate":"仅显示已连接节点"},
  {"dir":"src/cli/nodes-cli/register.status.ts","origin":"Only show nodes connected within duration (e.g. 24h)","translate":"仅显示指定时间内连接过的节点 (如 24h)"},
  {"dir":"src/cli/nodes-cli/register.status.ts","origin":"Invalid --last-connected","translate":"无效的 --last-connected"},
  {"dir":"src/cli/nodes-cli/register.invoke.ts","origin":"Invoke a command on a paired node","translate":"在已配对节点上调用命令"},
  {"dir":"src/cli/nodes-cli/register.invoke.ts","origin":"Command (e.g. canvas.eval)","translate":"命令 (如 canvas.eval)"},
  {"dir":"src/cli/nodes-cli/register.invoke.ts","origin":"JSON object string for params","translate":"参数的 JSON 对象字符串"},
  {"dir":"src/cli/nodes-cli/register.invoke.ts","origin":"Node invoke timeout in ms (default 15000)","translate":"节点调用超时毫秒数 (默认 15000)"},
  {"dir":"src/cli/nodes-cli/register.invoke.ts","origin":"Idempotency key (optional)","translate":"幂等键 (可选)"},
  {"dir":"src/cli/nodes-cli/register.invoke.ts","origin":"--node and --command required","translate":"需要 --node 和 --command"},
  {"dir":"src/cli/nodes-cli/register.invoke.ts","origin":"Run a shell command on a node (mac only)","translate":"在节点上运行 Shell 命令 (仅限 mac)"},
  {"dir":"src/cli/nodes-cli/register.invoke.ts","origin":"Working directory","translate":"工作目录"},
  {"dir":"src/cli/nodes-cli/register.invoke.ts","origin":"Environment override (repeatable)","translate":"覆盖环境变量 (可重复)"},
  {"dir":"src/cli/nodes-cli/register.invoke.ts","origin":"Run a raw shell command string (sh -lc / cmd.exe /c)","translate":"运行原始 Shell 命令字符串 (sh -lc / cmd.exe /c)"},
  {"dir":"src/cli/nodes-cli/register.invoke.ts","origin":"Agent id (default: configured default agent)","translate":"Agent ID (默认: 配置的默认 Agent)"},
  {"dir":"src/cli/nodes-cli/register.invoke.ts","origin":"Exec ask mode (off|on-miss|always)","translate":"执行询问模式 (off|on-miss|always)"},
  {"dir":"src/cli/nodes-cli/register.invoke.ts","origin":"Exec security mode (deny|allowlist|full)","translate":"执行安全模式 (deny|allowlist|full)"},
  {"dir":"src/cli/nodes-cli/register.invoke.ts","origin":"Command timeout (ms)","translate":"命令超时 (毫秒)"},
  {"dir":"src/cli/nodes-cli/register.invoke.ts","origin":"Require screen recording permission","translate":"需要屏幕录制权限"},
  {"dir":"src/cli/nodes-cli/register.invoke.ts","origin":"Node invoke timeout in ms (default 30000)","translate":"节点调用超时毫秒数 (默认 30000)"},
  {"dir":"src/cli/nodes-cli/register.invoke.ts","origin":"Command and args","translate":"命令和参数"},
  {"dir":"src/cli/nodes-cli/register.invoke.ts","origin":"use --raw or argv, not both","translate":"使用 --raw 或 argv，不能同时使用"},
  {"dir":"src/cli/nodes-cli/register.invoke.ts","origin":"command required","translate":"需要命令"},
  {"dir":"src/cli/nodes-cli/register.invoke.ts","origin":"node required (set --node or tools.exec.node)","translate":"需要节点 (设置 --node 或 tools.exec.node)"}
]